COPYING.txt
MANIFEST.in
README.md
package_variables.py
requirements.txt
setup.py
spectral_libraries/__init__.py
spectral_libraries/spectral_libraries_plugin.py
spectral_libraries.egg-info/PKG-INFO
spectral_libraries.egg-info/SOURCES.txt
spectral_libraries.egg-info/dependency_links.txt
spectral_libraries.egg-info/entry_points.txt
spectral_libraries.egg-info/top_level.txt
spectral_libraries/core/__init__.py
spectral_libraries/core/amuses.py
spectral_libraries/core/cres.py
spectral_libraries/core/ear_masa_cob.py
spectral_libraries/core/ies.py
spectral_libraries/core/library_metrics.py
spectral_libraries/core/music.py
spectral_libraries/core/square_array.py
spectral_libraries/images/average.png
spectral_libraries/images/cube.png
spectral_libraries/images/iteration.png
spectral_libraries/images/music.png
spectral_libraries/images/percentage.png
spectral_libraries/images/profile.png
spectral_libraries/images/prune.png
spectral_libraries/interfaces/__init__.py
spectral_libraries/interfaces/amuses.ui
spectral_libraries/interfaces/amuses_gui.py
spectral_libraries/interfaces/cres.ui
spectral_libraries/interfaces/cres_gui.py
spectral_libraries/interfaces/ear_masa_cob.ui
spectral_libraries/interfaces/ear_masa_cob_cli.py
spectral_libraries/interfaces/ear_masa_cob_gui.py
spectral_libraries/interfaces/exports.py
spectral_libraries/interfaces/ies.ui
spectral_libraries/interfaces/ies_cli.py
spectral_libraries/interfaces/ies_gui.py
spectral_libraries/interfaces/imports.py
spectral_libraries/interfaces/music.ui
spectral_libraries/interfaces/music_gui.py
spectral_libraries/interfaces/spectral_library_gui.py
spectral_libraries/interfaces/square_array.ui
spectral_libraries/interfaces/square_array_cli.py
spectral_libraries/interfaces/square_array_gui.py
spectral_libraries/qps/__init__.py
spectral_libraries/qps/cursorlocationvalue.py
spectral_libraries/qps/layerproperties.py
spectral_libraries/qps/maptools.py
spectral_libraries/qps/models.py
spectral_libraries/qps/qgisclasses.py
spectral_libraries/qps/resources.py
spectral_libraries/qps/searchfiledialog.py
spectral_libraries/qps/setup.py
spectral_libraries/qps/simplewidgets.py
spectral_libraries/qps/subdatasets.py
spectral_libraries/qps/testing.py
