Metadata-Version: 2.1
Name: spectral-libraries
Version: 1.1.1
Summary: Creating spectral libraries interactively (selecting spectra from an image or using regions of interest); visualizing the library on a plot and managing the metadata (developed by HU Berlin); Optimizing spectral libraries with IES, Ear-Masa-Cob, CRES, MUSIC, AMUSES.
Home-page: https://bitbucket.org/kul-reseco/spectral-libraries
Author: Ann Crabbé
Author-email: acrabbe.foss@gmail.com
License: UNKNOWN
Project-URL: Documentation, https://spectral-libraries.readthedocs.io
Project-URL: Source Code, https://bitbucket.org/kul-reseco/spectral-libraries/src
Project-URL: Issue Tracker, https://bitbucket.org/kul-reseco/spectral-libraries/issues
Keywords: ies,ear,masa,cob,emc,cres,square array,spectral library,remote sensing,viper,endmember,spectral signal,music,amuses
Platform: UNKNOWN
